db_commuter/__init__.py
db_commuter/commuters.py
db_commuter/connections.py
db_commuter/version.py
db_commuter-0.1.13.dist-info/LICENSE
db_commuter-0.1.13.dist-info/METADATA
db_commuter-0.1.13.dist-info/WHEEL
db_commuter-0.1.13.dist-info/top_level.txt
db_commuter-0.1.13.dist-info/RECORD
