Metadata-Version: 2.1
Name: db-commuter
Version: 0.1.13
Summary: Database communication manager
Home-page: https://github.com/viktorsapozhok/db-commuter
Author: Alex Piskun
Author-email: piskun.aleksey@gmail.com
License: UNKNOWN
Platform: UNKNOWN
Classifier: Programming Language :: Python :: 3
Classifier: License :: OSI Approved :: MIT License
Classifier: Operating System :: OS Independent
Requires-Python: >=3.6
Requires-Dist: pandas (>=0.24.0)
Requires-Dist: sqlalchemy (>=1.3.3)
Requires-Dist: psycopg2-binary (>=2.7.7)
